mycobot_mcp/__init__.py
mycobot_mcp/camera.py
mycobot_mcp/object_detection.py
mycobot_mcp/py.typed
mycobot_mcp/rle_utils.py
mycobot_mcp/robot_controller.py
mycobot_mcp/robot_operator.py
mycobot_mcp/server.py
mycobot_mcp/settings.py
mycobot_mcp-0.1.1.dist-info/METADATA
mycobot_mcp-0.1.1.dist-info/WHEEL
mycobot_mcp-0.1.1.dist-info/entry_points.txt
mycobot_mcp-0.1.1.dist-info/licenses/LICENSE
mycobot_mcp-0.1.1.dist-info/RECORD
