Metadata-Version: 2.4
Name: mycobot-mcp
Version: 0.1.1
Summary: Add your description here
Author-email: neka-nat <nekanat.stock@gmail.com>
License-File: LICENSE
Requires-Python: >=3.12
Requires-Dist: dds-cloudapi-sdk>=0.4.1
Requires-Dist: kinpy>=0.4.2
Requires-Dist: loguru>=0.7.3
Requires-Dist: mcp[cli]>=1.6.0
Requires-Dist: opencv-python>=4.11.0.86
Requires-Dist: pydantic>=2.11.3
Requires-Dist: pymycobot>=3.9.7
Requires-Dist: supervision>=0.25.1
